magento_2_api/__init__.py
magento_2_api/magento_api.py
magento_2_api-0.1.3.dist-info/LICENSE
magento_2_api-0.1.3.dist-info/METADATA
magento_2_api-0.1.3.dist-info/WHEEL
magento_2_api-0.1.3.dist-info/top_level.txt
magento_2_api-0.1.3.dist-info/RECORD
