Metadata-Version: 2.1
Name: magento-2-api
Version: 0.1.3
Summary: A python module for interacting with the Magento 2 REST API.
Home-page: https://github.com/dmarler/python-magento-2-api
Author: Dalton Marler
Author-email: daltonmarler@outlook.com
License: UNKNOWN
Project-URL: Bug Tracker, https://github.com/dmarler/python-magento-2-api/issues
Platform: UNKNOWN
Classifier: Programming Language :: Python :: 3
Classifier: License :: OSI Approved :: MIT License
Classifier: Operating System :: OS Independent
Classifier: Development Status :: 1 - Planning
Requires-Python: >=3.6
License-File: LICENSE
Requires-Dist: requests
